prebuilt_binaries.py
prebuilt_binaries-0.5.0.dist-info/LICENSE
prebuilt_binaries-0.5.0.dist-info/METADATA
prebuilt_binaries-0.5.0.dist-info/WHEEL
prebuilt_binaries-0.5.0.dist-info/entry_points.txt
prebuilt_binaries-0.5.0.dist-info/top_level.txt
prebuilt_binaries-0.5.0.dist-info/RECORD
