Metadata-Version: 2.1
Name: prebuilt-binaries
Version: 0.5.0
Summary: A setuptools command for packaging pre-built binary python extension modules.
Home-page: https://github.com/tim-mitchell/prebuilt_binaries
Author: Tim Mitchell
Author-email: tim.mitchell@seequent.com
Keywords: packaging,extension,setuptools
Classifier: Framework :: Setuptools Plugin
Classifier: Programming Language :: Python :: 3
Classifier: License :: OSI Approved :: MIT License
Classifier: Topic :: Software Development :: Build Tools
License-File: LICENSE
